idr/__init__.py
idr/__main__.py
idr/enhancer.py
image_illumination_restoration-0.1.3.dist-info/licenses/License
image_illumination_restoration-0.1.3.dist-info/METADATA
image_illumination_restoration-0.1.3.dist-info/WHEEL
image_illumination_restoration-0.1.3.dist-info/top_level.txt
image_illumination_restoration-0.1.3.dist-info/RECORD
