Metadata-Version: 2.4
Name: image-illumination-restoration
Version: 0.1.3
Summary: Image_Illumination_&_Restoration
Author: Rudransh Joshi
Author-email: rudransh20septmber@gmail.com
Classifier: Programming Language :: Python :: 3
Classifier: License :: OSI Approved :: MIT License
Classifier: Operating System :: OS Independent
Requires-Python: >=3.7
License-File: License
Requires-Dist: opencv-python
Requires-Dist: numpy
Dynamic: author
Dynamic: author-email
Dynamic: classifier
Dynamic: description
Dynamic: description-content-type
Dynamic: license-file
Dynamic: requires-dist
Dynamic: requires-python
Dynamic: summary
